eryn/CMakeLists.txt
eryn/__init__.py
eryn/backends/__init__.py
eryn/backends/backend.py
eryn/backends/hdfbackend.py
eryn/ensemble.py
eryn/git_version.py.in
eryn/model.py
eryn/moves/__init__.py
eryn/moves/combine.py
eryn/moves/delayedrejection.py
eryn/moves/distgen.py
eryn/moves/distgenrj.py
eryn/moves/gaussian.py
eryn/moves/group.py
eryn/moves/groupstretch.py
eryn/moves/mh.py
eryn/moves/move.py
eryn/moves/mtdistgen.py
eryn/moves/mtdistgenrj.py
eryn/moves/multipletry.py
eryn/moves/red_blue.py
eryn/moves/rj.py
eryn/moves/stretch.py
eryn/moves/tempering.py
eryn/pbar.py
eryn/prior.py
eryn/state.py
eryn/tests/__init__.py
eryn/tests/test_eryn.py
eryn/utils/__init__.py
eryn/utils/periodic.py
eryn/utils/stopping.py
eryn/utils/transform.py
eryn/utils/updates.py
eryn/utils/utility.py
eryn-1.2.3.dist-info/WHEEL
eryn-1.2.3.dist-info/METADATA
eryn-1.2.3.dist-info/RECORD
