Metadata-Version: 2.3
Name: eryn
Version: 1.2.3
Summary: Eryn: an omni-MCMC sampling package.
Author: Michael Katz
Author-email: Michael Katz <mikekatz04@gmail.com>
Classifier: License :: OSI Approved :: Apache Software License
Classifier: Natural Language :: English
Classifier: Programming Language :: C++
Classifier: Programming Language :: Cython
Classifier: Programming Language :: Python :: 3 :: Only
Classifier: Programming Language :: Python :: 3.9
Classifier: Programming Language :: Python :: 3.10
Classifier: Programming Language :: Python :: 3.11
Classifier: Programming Language :: Python :: 3.12
Classifier: Programming Language :: Python :: 3.13
Requires-Dist: exceptiongroup ; python_full_version < '3.11'
Requires-Dist: h5py
Requires-Dist: jsonschema
Requires-Dist: matplotlib
Requires-Dist: numpy
Requires-Dist: nvidia-ml-py
Requires-Dist: platformdirs
Requires-Dist: pydantic
Requires-Dist: pyyaml
Requires-Dist: requests
Requires-Dist: rich
Requires-Dist: scipy
Requires-Dist: tqdm
Requires-Dist: wrapt
Requires-Dist: ipykernel ; extra == 'doc'
Requires-Dist: ipython ; extra == 'doc'
Requires-Dist: ipywidgets ; extra == 'doc'
Requires-Dist: myst-parser ; extra == 'doc'
Requires-Dist: nbsphinx ; extra == 'doc'
Requires-Dist: pypandoc ; extra == 'doc'
Requires-Dist: sphinx ; extra == 'doc'
Requires-Dist: sphinx-rtd-theme ; extra == 'doc'
Requires-Dist: sphinx-tippy ; extra == 'doc'
Requires-Dist: corner ; extra == 'doc'
Requires-Dist: matplotlib ; extra == 'testing'
Requires-Dist: corner ; extra == 'testing'
Requires-Dist: chainconsumer ; extra == 'testing'
Requires-Python: >=3.9
Provides-Extra: doc
Provides-Extra: testing
